accretion_workers/__init__.py
accretion_workers/_util.py
accretion_workers/_internal/__init__.py
accretion_workers/artifact_builder/__init__.py
accretion_workers/artifact_builder/requirements_parser.py
accretion_workers/artifact_builder/zip_builder.py
accretion_workers/layer_builder/__init__.py
accretion_workers/layer_builder/artifact_checker.py
accretion_workers/layer_builder/event_filter.py
accretion_workers/layer_builder/version_publisher.py
accretion_workers-0.1.0.dist-info/LICENSE
accretion_workers-0.1.0.dist-info/METADATA
accretion_workers-0.1.0.dist-info/WHEEL
accretion_workers-0.1.0.dist-info/top_level.txt
accretion_workers-0.1.0.dist-info/RECORD
