Metadata-Version: 2.1
Name: accretion-workers
Version: 0.1.0
Summary: Accretion workers.
Home-page: https://github.com/mattsb42/accretion
Author: mattsb42
Author-email: m@ttsb42.com
Maintainer: mattsb42
License: Apache License 2.0
Keywords: aws lambda accretion
Platform: UNKNOWN
Classifier: Development Status :: 4 - Beta
Classifier: Intended Audience :: Developers
Classifier: Natural Language :: English
Classifier: License :: OSI Approved :: Apache Software License
Classifier: Programming Language :: Python
Classifier: Programming Language :: Python :: 3.6
Classifier: Programming Language :: Python :: 3.7
Classifier: Programming Language :: Python :: Implementation :: CPython
Classifier: Topic :: System :: Archiving :: Packaging
Requires-Dist: boto3 (>=1.9.58)
Requires-Dist: accretion-common (>=0.1.1)
